ipywardley/__init__.py
ipywardley/wardley.py
ipywardley-0.0.7.dist-info/LICENSE
ipywardley-0.0.7.dist-info/WHEEL
ipywardley-0.0.7.dist-info/METADATA
ipywardley-0.0.7.dist-info/RECORD
