Metadata-Version: 2.1
Name: ipywardley
Version: 0.0.7
Summary: Bringing Wardley Map magic to Jupyter notebooks.
Home-page: https://github.com/anjackson/ipywardley
Author: Andrew N. Jackson
Author-email: anj@anjackson.net
Classifier: License :: OSI Approved :: Apache Software License
Requires-Dist: ipython
Requires-Dist: matplotlib
Requires-Dist: jupyterlab ; extra == "test"
Provides-Extra: test
